.gitignore
PKG-INFO
README.md
pyproject.toml
bec_lib/__init__.py
bec_lib/_print_versions.py
bec_lib/acl_login.py
bec_lib/alarm_handler.py
bec_lib/atlas_models.py
bec_lib/bec_errors.py
bec_lib/bec_service.py
bec_lib/bec_yaml_loader.py
bec_lib/bl_checks.py
bec_lib/bl_conditions.py
bec_lib/callback_handler.py
bec_lib/channel_monitor.py
bec_lib/client.py
bec_lib/codecs.py
bec_lib/config_helper.py
bec_lib/connector.py
bec_lib/dap_plugin_objects.py
bec_lib/dap_plugins.py
bec_lib/device.py
bec_lib/device_monitor_plugin.py
bec_lib/devicemanager.py
bec_lib/endpoints.py
bec_lib/file_utils.py
bec_lib/live_scan_data.py
bec_lib/lmfit_serializer.py
bec_lib/logbook_connector.py
bec_lib/logger.py
bec_lib/macro_update_handler.py
bec_lib/messages.py
bec_lib/metadata_schema.py
bec_lib/numpy_encoder.py
bec_lib/observer.py
bec_lib/pdf_writer.py
bec_lib/plugin_helper.py
bec_lib/queue_items.py
bec_lib/redis_connector.py
bec_lib/request_items.py
bec_lib/scan_data_container.py
bec_lib/scan_history.py
bec_lib/scan_items.py
bec_lib/scan_manager.py
bec_lib/scan_number_container.py
bec_lib/scan_report.py
bec_lib/scans.py
bec_lib/scibec_validator.py
bec_lib/script_executor.py
bec_lib/serialization.py
bec_lib/serialization_registry.py
bec_lib/service_config.py
bec_lib/signature_serializer.py
bec_lib/user_macros.py
bec_lib/configs/__init__.py
bec_lib/configs/demo_config.yaml
bec_lib/configs/openapi_schema.json
bec_lib/procedures/__init__.py
bec_lib/procedures/helper.py
bec_lib/procedures/hli.py
bec_lib/procedures/status.py
bec_lib/tests/__init__.py
bec_lib/tests/fixtures.py
bec_lib/tests/test_config.yaml
bec_lib/tests/test_service_config.yaml
bec_lib/tests/utils.py
bec_lib/utils/__init__.py
bec_lib/utils/copier_jinja_filters.py
bec_lib/utils/import_utils.py
bec_lib/utils/json.py
bec_lib/utils/proxy.py
bec_lib/utils/pydantic_pretty_print.py
bec_lib/utils/rpc_utils.py
bec_lib/utils/scan_utils.py
bec_lib/utils/threading_utils.py
bec_lib/utils/user_acls_test.py
bec_lib-3.94.0.dist-info/METADATA
bec_lib-3.94.0.dist-info/WHEEL
bec_lib-3.94.0.dist-info/entry_points.txt
bec_lib-3.94.0.dist-info/RECORD
