Metadata-Version: 2.4
Name: bec_lib
Version: 3.94.0
Summary: BEC library
Project-URL: Bug Tracker, https://github.com/bec-project/bec/issues
Project-URL: Homepage, https://github.com/bec-project/bec
Classifier: Development Status :: 3 - Alpha
Classifier: Programming Language :: Python :: 3
Classifier: Topic :: Scientific/Engineering
Requires-Python: >=3.11
Requires-Dist: fastjsonschema~=2.19
Requires-Dist: fpdf2>=2.7.7,~=2.7
Requires-Dist: h5py~=3.10
Requires-Dist: hdf5plugin<6.0,>=4.3
Requires-Dist: hiredis~=3.0
Requires-Dist: lmfit~=1.3
Requires-Dist: loguru~=0.7
Requires-Dist: louie~=2.0
Requires-Dist: msgpack>1.0.4,~=1.0
Requires-Dist: numpy<3.0,>=1.24
Requires-Dist: prettytable~=3.9
Requires-Dist: psutil~=5.9
Requires-Dist: pydantic<2.12.0,~=2.8
Requires-Dist: pylint~=3.0
Requires-Dist: python-dotenv~=1.0
Requires-Dist: python-slugify~=8.0
Requires-Dist: pyyaml~=6.0
Requires-Dist: redis>=6.2.0,~=6.2
Requires-Dist: requests~=2.31
Requires-Dist: rich~=13.7
Requires-Dist: scipy~=1.12
Requires-Dist: tomli>=2.0.1,~=2.0
Requires-Dist: toolz~=0.12
Requires-Dist: typeguard>=4.1.5,~=4.1
Provides-Extra: ci
Requires-Dist: bec-testing-plugin; extra == 'ci'
Provides-Extra: dev
Requires-Dist: black~=25.0; extra == 'dev'
Requires-Dist: copier~=9.7; extra == 'dev'
Requires-Dist: coverage~=7.0; extra == 'dev'
Requires-Dist: fakeredis>=2.23.2,~=2.23; extra == 'dev'
Requires-Dist: isort>=5.13.2,~=5.13; extra == 'dev'
Requires-Dist: jinja2~=3.1; extra == 'dev'
Requires-Dist: pandas~=2.0; extra == 'dev'
Requires-Dist: pytest-random-order~=1.1; extra == 'dev'
Requires-Dist: pytest-redis~=3.0; extra == 'dev'
Requires-Dist: pytest-timeout~=2.2; extra == 'dev'
Requires-Dist: pytest~=8.0; extra == 'dev'
Requires-Dist: typer~=0.15; extra == 'dev'
